camptools/__init__.py
camptools/checkpoint.py
camptools/cmdjob.py
camptools/collect_report.py
camptools/conversion_unit.py
camptools/create_vdist.py
camptools/extent_sim.py
camptools/filesync.py
camptools/job_history.py
camptools/job_status.py
camptools/jobs.py
camptools/latest_job.py
camptools/mymkdir.py
camptools/preinp.py
camptools/preinp_grammer.lark
camptools/qsub_wrapper.py
camptools/settings.py
camptools/utils.py
camptools/grand/__init__.py
camptools/grand/mypjsub.py
camptools/grand/pjsub_wrapper.py
camptools/job_scheduler/__init__.py
camptools/job_scheduler/core.py
camptools/job_scheduler/laurel.py
camptools/job_scheduler/sbatch_wrapper.py
camptools/job_scheduler/throw_job_wrapper.py
camptools/param_sweep/__init__.py
camptools/param_sweep/case.py
camptools/param_sweep/cli.py
camptools/param_sweep/config.py
camptools/param_sweep/naming.py
camptools/param_sweep/renderer.py
camptools/param_sweep/runner.py
camptools/setup_env/__init__.py
camptools/setup_env/setup_camphor.py
camptools/simmanager/__init__.py
camptools/simmanager/copylist.py
camptools/simmanager/simmanager.py
camptools/simmanager/utils.py
camptools-0.13.0.dist-info/licenses/LICENSE
camptools-0.13.0.dist-info/METADATA
camptools-0.13.0.dist-info/WHEEL
camptools-0.13.0.dist-info/entry_points.txt
camptools-0.13.0.dist-info/top_level.txt
camptools-0.13.0.dist-info/RECORD
