Metadata-Version: 2.4
Name: camptools
Version: 0.13.0
Summary: Tools for camphor
Author-email: Nkzono <71783375+Nkzono99@users.noreply.github.com>
License: MIT
Classifier: Programming Language :: Python :: 3
Classifier: License :: OSI Approved :: MIT License
Classifier: Operating System :: OS Independent
Requires-Python: >=3.7
License-File: LICENSE
Requires-Dist: f90nml
Requires-Dist: numpy
Requires-Dist: emout
Requires-Dist: lark
Requires-Dist: pyyaml
Requires-Dist: jsonschema
Requires-Dist: jinja2
Requires-Dist: colorama
Dynamic: license-file
